fastnet/__init__.py
fastnet/data_manager.py
fastnet/defaults.py
fastnet/example.py
fastnet/log.py
fastnet/metrics.py
fastnet/relevance.py
fastnet/train.py
fastnet/utils.py
fastnet-1.0.0.dist-info/LICENSE
fastnet-1.0.0.dist-info/METADATA
fastnet-1.0.0.dist-info/WHEEL
fastnet-1.0.0.dist-info/top_level.txt
fastnet-1.0.0.dist-info/RECORD
